{
    "realm": "ecommerce",
    "enabled": true,
    "roles": {
        "realm": [{ "name": "admin" }, { "name": "vendor" }, { "name": "customer" }]
    },
    "clients": [
        {
            "clientId": "laravel-app",
            "enabled": true,
            "publicClient": false,
            "secret": "3g589P8lm9r6amOnXO7Yqdh9TdmDT3JA",
            "redirectUris": ["http://localhost:8000/*"],
            "webOrigins": ["http://localhost:8000"],
            "standardFlowEnabled": true,
            "directAccessGrantsEnabled": true
        }
    ],
    "identityProviders": [
        {
            "alias": "google",
            "displayName": "Google",
            "providerId": "google",
            "enabled": true,
            "trustEmail": true,
            "storeToken": true,
            "addReadTokenRoleOnCreate": true,
            "config": {
                "clientId": "YOUR_GOOGLE_CLIENT_ID",
                "clientSecret": "YOUR_GOOGLE_CLIENT_SECRET",
                "guiOrder": "1"
            }
        }
    ]
}
